<?xml version="1.0" encoding="UTF-8"?>
<inforef>
  <fileref>
    <file>
      <id>183631</id>
    </file>
    <file>
      <id>183632</id>
    </file>
    <file>
      <id>183633</id>
    </file>
    <file>
      <id>183634</id>
    </file>
    <file>
      <id>183635</id>
    </file>
    <file>
      <id>183636</id>
    </file>
    <file>
      <id>183637</id>
    </file>
    <file>
      <id>183638</id>
    </file>
    <file>
      <id>183639</id>
    </file>
    <file>
      <id>183640</id>
    </file>
    <file>
      <id>183641</id>
    </file>
    <file>
      <id>183642</id>
    </file>
    <file>
      <id>183643</id>
    </file>
    <file>
      <id>183644</id>
    </file>
    <file>
      <id>183645</id>
    </file>
    <file>
      <id>183646</id>
    </file>
    <file>
      <id>183647</id>
    </file>
    <file>
      <id>183648</id>
    </file>
    <file>
      <id>183649</id>
    </file>
    <file>
      <id>183650</id>
    </file>
  </fileref>
</inforef>